generi/__init__.py
generi/artifact.py
generi/cli.py
generi/commands/__init__.py
generi/commands/build.py
generi/commands/push.py
generi/commands/write.py
generi/config/__init__.py
generi/config/config.py
generi/config/registry.py
generi/optim.py
generi-0.2.0.dist-info/entry_points.txt
generi-0.2.0.dist-info/LICENSE
generi-0.2.0.dist-info/WHEEL
generi-0.2.0.dist-info/METADATA
generi-0.2.0.dist-info/RECORD
