Metadata-Version: 2.1
Name: generi
Version: 0.2.0
Summary: Manage huge sets of Docker images using matrix builds
Home-page: https://github.com/nick-lehmann/Generi
License: MIT
Keywords: docker,CI,templating
Author: Nick Lehmann
Author-email: nick@lehmann.sh
Requires-Python: >=3.7
Classifier: Development Status :: 2 - Pre-Alpha
Classifier: Environment :: Console
Classifier: License :: OSI Approved :: MIT License
Classifier: Programming Language :: Python
Classifier: Programming Language :: Python :: 3
Classifier: Programming Language :: Python :: 3 :: Only
Classifier: Programming Language :: Python :: 3.7
Classifier: Programming Language :: Python :: 3.8
Classifier: Programming Language :: Python :: 3.9
Classifier: Typing :: Typed
Requires-Dist: Jinja2 (>=2.10.3,<3.0.0)
Requires-Dist: aiodocker (>=0.17.0,<0.18.0)
Requires-Dist: fire (>=0.2.1,<0.3.0)
Requires-Dist: pyyaml (>=5.2,<6.0)
Project-URL: Bug Tracker, https://github.com/nick-lehmann/Generi/issues
Project-URL: Documentation, https://generi.nicklehmann.sh
Project-URL: Repository, https://github.com/nick-lehmann/Generi
